engine/__init__.py
engine/client.py
engine/control_db.py
engine/handler.py
engine/listen.py
sqlite_sync/__init__.py
sqlite_sync/client.py
sqlite_sync/control_db.py
sqlite_sync/handler.py
sqlite_sync/listen.py
sqlite_sync-0.0.8.dist-info/METADATA
sqlite_sync-0.0.8.dist-info/WHEEL
sqlite_sync-0.0.8.dist-info/top_level.txt
sqlite_sync-0.0.8.dist-info/RECORD
