Metadata-Version: 2.1
Name: sqlite-sync
Version: 0.0.8
Summary: SQLite3 wrapper for query synchronization
Home-page: https://github.com/RobertMeow/sqlite_sync
Author: Robert Popov
Author-email: robert@berht.dev
